tacrpy/__init__.py
tacrpy/analytics/__init__.py
tacrpy/nlp/__init__.py
tacrpy/nlp/fulltext.py
tacrpy/nlp/preprocessing.py
tacrpy/nlp/semantic.py
pojdte_pane_budeme_hrat_slovni_fotbal-1.0.2.dist-info/METADATA
pojdte_pane_budeme_hrat_slovni_fotbal-1.0.2.dist-info/WHEEL
pojdte_pane_budeme_hrat_slovni_fotbal-1.0.2.dist-info/top_level.txt
pojdte_pane_budeme_hrat_slovni_fotbal-1.0.2.dist-info/RECORD
