Metadata-Version: 2.4
Name: pojdte-pane-budeme-hrat-slovni-fotbal
Version: 1.0.2
Summary: Potkali se u Kolína
Author: velci panove tacru
Author-email: rozalie.bilkova@tacr.cz
Project-URL: Documentation, https://youtu.be/QprFGNxrMj0?feature=shared
Requires-Dist: pojdte-pane-budeme-si-hrat
Requires-Dist: pandas
Requires-Dist: gspread
Requires-Dist: numpy
Requires-Dist: sentence-transformers
Requires-Dist: nltk
Requires-Dist: requests
Requires-Dist: corpy
Requires-Dist: unidecode
Dynamic: author
Dynamic: author-email
Dynamic: description
Dynamic: project-url
Dynamic: requires-dist
Dynamic: summary
